pyexe/__init__.py
pyexe/__main__.py
pyexe/builder.py
pyexe/cli.py
python_exe-0.1.0.dist-info/METADATA
python_exe-0.1.0.dist-info/WHEEL
python_exe-0.1.0.dist-info/entry_points.txt
python_exe-0.1.0.dist-info/top_level.txt
python_exe-0.1.0.dist-info/RECORD
