Metadata-Version: 2.4
Name: python-exe
Version: 0.1.0
Summary: My Python package
Author-email: Your Name <you@example.com>
Requires-Python: >=3.7
